airflow_mcd/__init__.py
airflow_mcd/callbacks/client.py
airflow_mcd/callbacks/mcd_callbacks.py
airflow_mcd/callbacks/utils.py
airflow_mcd/hooks/__init__.py
airflow_mcd/hooks/constants.py
airflow_mcd/hooks/gateway_session_hook.py
airflow_mcd/hooks/session_hook.py
airflow_mcd/operators/__init__.py
airflow_mcd/operators/base_operator.py
airflow_mcd/operators/circuit_breaker_operators.py
airflow_mcd/operators/dbt.py
airflow_mcd-0.3.11.dist-info/LICENSE
airflow_mcd-0.3.11.dist-info/METADATA
airflow_mcd-0.3.11.dist-info/WHEEL
airflow_mcd-0.3.11.dist-info/entry_points.txt
airflow_mcd-0.3.11.dist-info/top_level.txt
airflow_mcd-0.3.11.dist-info/RECORD
