Metadata-Version: 2.1
Name: airflow_mcd
Version: 0.3.11
Summary: Monte Carlo's Apache Airflow Provider
Home-page: https://www.montecarlodata.com/
Author: Monte Carlo Data, Inc
Author-email: info@montecarlodata.com
License: Apache Software License (Apache 2.0)
Classifier: Development Status :: 5 - Production/Stable
Classifier: Intended Audience :: Developers
Classifier: Natural Language :: English
Classifier: Topic :: Software Development :: Build Tools
Classifier: License :: OSI Approved :: Apache Software License
Classifier: Programming Language :: Python :: 3.7
Classifier: Programming Language :: Python :: 3.8
Classifier: Programming Language :: Python :: 3.9
Classifier: Programming Language :: Python :: 3.10
Classifier: Programming Language :: Python :: 3.11
Classifier: Programming Language :: Python :: 3.12
Requires-Python: >=3.7
License-File: LICENSE
Requires-Dist: pycarlo (>=0.10.5)
Requires-Dist: packaging (>=21)
Requires-Dist: importlib-metadata (>=4) ; python_version < "3.8"
